nutshell/__init__.py
nutshell/model.py
nutshell/utils.py
nutshell/algorithms/__init__.py
nutshell/algorithms/information_retrieval.py
nutshell/algorithms/ranking.py
nutshell/algorithms/similarity.py
nutshell/preprocessing/__init__.py
nutshell/preprocessing/cleaner.py
nutshell/preprocessing/preprocessor.py
nutshell/preprocessing/tokenizer.py
pynutshell-1.0.2.dist-info/LICENSE
pynutshell-1.0.2.dist-info/METADATA
pynutshell-1.0.2.dist-info/WHEEL
pynutshell-1.0.2.dist-info/top_level.txt
pynutshell-1.0.2.dist-info/RECORD
