Metadata-Version: 2.1
Name: pynutshell
Version: 1.0.2
Summary: An unsupervised text summarization and information retrieval library under the hood using natural language processing models.
Home-page: https://github.com/KrishnanSG/Nutshell
Author: Krishnan S G, Shruthi Abirami
Author-email: krishsg525@gmail.com
License: UNKNOWN
Keywords: text,summarization,nutshell,ranking,information,retrieval,similarity,keyword,extraction,nlp,natural,language,nltk,tokenizer,pagerank,textrank,bm25plus
Platform: UNKNOWN
Classifier: Programming Language :: Python :: 3
Classifier: License :: OSI Approved :: MIT License
Classifier: Operating System :: OS Independent
Requires-Python: >=3.6
Requires-Dist: numpy
Requires-Dist: networkx
Requires-Dist: nltk
